Metadata-Version: 2.2
Name: ghae
Version: 1.0.1
Summary: This library detects the responses to erroneous requests to the GitHub API. An exception signals these errors.
Home-page: https://github.com/GRV96/ghae
Author: Guyllaume Rousseau
License: MIT
Classifier: Development Status :: 5 - Production/Stable
Classifier: Intended Audience :: Developers
Classifier: License :: OSI Approved :: MIT License
Classifier: Operating System :: OS Independent
Classifier: Programming Language :: Python :: 3
Classifier: Topic :: Software Development :: Libraries
Classifier: Topic :: Software Development :: Version Control :: Git
Classifier: Topic :: Utilities
License-File: LICENSE
Dynamic: author
Dynamic: classifier
Dynamic: description
Dynamic: description-content-type
Dynamic: home-page
Dynamic: license
Dynamic: summary
